broqer/__init__.py
broqer/_version.py
broqer/coro_queue.py
broqer/disposable.py
broqer/error_handler.py
broqer/operator.py
broqer/operator_overloading.py
broqer/publisher.py
broqer/subscriber.py
broqer/timer.py
broqer/types.py
broqer/value.py
broqer/op/__init__.py
broqer/op/bitwise.py
broqer/op/cache.py
broqer/op/combine_latest.py
broqer/op/filter_.py
broqer/op/map_.py
broqer/op/map_async.py
broqer/op/py_operators.py
broqer/op/throttle.py
broqer/publishers/__init__.py
broqer/publishers/poll.py
broqer/subscribers/__init__.py
broqer/subscribers/on_emit_future.py
broqer/subscribers/sink.py
broqer/subscribers/sink_async.py
broqer/subscribers/trace.py
broqer-3.1.1.dist-info/licenses/LICENSE
broqer-3.1.1.dist-info/METADATA
broqer-3.1.1.dist-info/WHEEL
broqer-3.1.1.dist-info/top_level.txt
broqer-3.1.1.dist-info/RECORD
