Metadata-Version: 2.4
Name: broqer
Version: 3.1.1
Summary: Carefully crafted library to operate with continuous streams of data in a reactive style with publish/subscribe and broker functionality.
Home-page: https://github.com/semiversus/python-broqer
Author: Günther Jena
Author-email: guenther@jena.at
License: MIT license
Keywords: broker publisher subscriber reactive frp observable
Classifier: Development Status :: 5 - Production/Stable
Classifier: Intended Audience :: Developers
Classifier: License :: OSI Approved :: MIT License
Classifier: Natural Language :: English
Classifier: Programming Language :: Python :: 3
Classifier: Programming Language :: Python :: 3.7
Classifier: Programming Language :: Python :: 3.8
Classifier: Programming Language :: Python :: 3.9
Classifier: Programming Language :: Python :: 3.10
Classifier: Programming Language :: Python :: 3.11
License-File: LICENSE
Dynamic: author
Dynamic: author-email
Dynamic: classifier
Dynamic: description
Dynamic: home-page
Dynamic: keywords
Dynamic: license
Dynamic: license-file
Dynamic: summary
